palette_diagram/__init__.py
palette_diagram/palette_diagram.py
palette_diagram-1.1.2.dist-info/LICENSE
palette_diagram-1.1.2.dist-info/METADATA
palette_diagram-1.1.2.dist-info/WHEEL
palette_diagram-1.1.2.dist-info/top_level.txt
palette_diagram-1.1.2.dist-info/RECORD
