Metadata-Version: 2.1
Name: palette-diagram
Version: 1.1.2
Summary: Visualization tool for collective categorical data
Home-page: https://github.com/chnoguchi/pip_test.git
Author: Chihiro Noguchi and Tatsuro Kawamoto
Author-email: chihiro3abc@gmail.com, kawamoto.tatsuro@gmail.com
License: UNKNOWN
Platform: UNKNOWN
Classifier: Programming Language :: Python :: 3
Classifier: License :: OSI Approved :: MIT License
Classifier: Operating System :: OS Independent
Requires-Python: >=3.7
Requires-Dist: numpy
Requires-Dist: pandas
Requires-Dist: scikit-learn
Requires-Dist: numba
Requires-Dist: matplotlib
Requires-Dist: seaborn
